pyhack/__init__.py
pyhack/core.py
pyhack-1.0.1.dist-info/LICENSE
pyhack-1.0.1.dist-info/METADATA
pyhack-1.0.1.dist-info/WHEEL
pyhack-1.0.1.dist-info/top_level.txt
pyhack-1.0.1.dist-info/RECORD
