Metadata-Version: 2.1
Name: pyhack
Version: 1.0.1
Summary: Hack with python easy!
Author: Mohammad Taha Gorji
Author-email: MohammadTahaGorjiProfile@gmail.com
Classifier: Programming Language :: Python :: 3
Classifier: License :: OSI Approved :: MIT License
Classifier: Operating System :: OS Independent
Requires-Python: >=3.6
License-File: LICENSE
Requires-Dist: rarfile
Requires-Dist: py7zr
Requires-Dist: PyPDF2
Requires-Dist: requests
